RPA_Hubspot.libspec
RPA/Hubspot.py
rpaframework_hubspot-1.0.2.dist-info/LICENSE
rpaframework_hubspot-1.0.2.dist-info/METADATA
rpaframework_hubspot-1.0.2.dist-info/WHEEL
rpaframework_hubspot-1.0.2.dist-info/RECORD
